poci/__init__.py
poci-0.1.0.dist-info/METADATA
poci-0.1.0.dist-info/WHEEL
poci-0.1.0.dist-info/RECORD
